chenosis/__init__.py
chenosis/client.py
chenosis/example.py
chenosis/exceptions.py
chenosis-0.1.0.dist-info/LICENSE
chenosis-0.1.0.dist-info/METADATA
chenosis-0.1.0.dist-info/WHEEL
chenosis-0.1.0.dist-info/top_level.txt
chenosis-0.1.0.dist-info/RECORD
