Metadata-Version: 2.1
Name: chenosis
Version: 0.1.0
Summary: A python client for MTN's Chenosis platform: https://chenosis.io.
Home-page: https://github.com/evanstjabadi/chenosis-python
Author: Evans Tjabadi
License: MIT
Classifier: Intended Audience :: Developers
Classifier: Operating System :: OS Independent
Classifier: Programming Language :: Python :: 3.10
Classifier: Programming Language :: Python :: 3.9
Classifier: Programming Language :: Python :: 3.8
Classifier: Programming Language :: Python :: 3.7
Classifier: Programming Language :: Python :: 3
Requires-Python: >=3.7
License-File: LICENSE
Requires-Dist: httpx (~=0.23.3)
